apc/__init__.py
apc/__main__.py
apc/apc.py
apc/config.py
apc/db.py
apc/web.py
apc/static/dygraph/dygraph.min.css
apc/static/dygraph/dygraph.min.js
apc/templates/index.html
APC_Power_Usage-0.1.5.dist-info/LICENSE.md
APC_Power_Usage-0.1.5.dist-info/METADATA
APC_Power_Usage-0.1.5.dist-info/WHEEL
APC_Power_Usage-0.1.5.dist-info/top_level.txt
APC_Power_Usage-0.1.5.dist-info/RECORD
